Metadata-Version: 2.1
Name: am_am_am_distributions
Version: 1.2
Summary: Gaussian distributions
License-File: license.txt
